{
	"status": "SUCCESS",
	"result": [{
		"informationSeqNo": 1011,
		"readCd": "1",
		"actionTypeCd": "0",
		"actionStartYmd": null,
		"actionEndYmd": null,
		"informationContentsTitle": "key_12345",
		"division": "投資情報部",
		"productCategoryCd": "DCM0001",
		"targetCd": "2",
		"viewStartYmdHm": "201912270000"
	}, {
		"informationSeqNo": 930,
		"readCd": "1",
		"actionTypeCd": "0",
		"actionStartYmd": null,
		"actionEndYmd": null,
		"informationContentsTitle": "HTML",
		"division": "投資情報部",
		"productCategoryCd": "DCM0010",
		"targetCd": "1",
		"viewStartYmdHm": "201911270000"
	}, {
		"informationSeqNo": 876,
		"readCd": "1",
		"actionTypeCd": "1",
		"actionStartYmd": "20191022",
		"actionEndYmd": "20201023",
		"informationContentsTitle": "yoshizawa!!!",
		"division": "商品マーケティング企画部",
		"productCategoryCd": "DCM0010",
		"targetCd": "1",
		"viewStartYmdHm": "201910210000"
	}, {
		"informationSeqNo": 102,
		"readCd": "1",
		"actionTypeCd": "1",
		"actionStartYmd": "20190531",
		"actionEndYmd": "20190731",
		"informationContentsTitle": "タイトルが長い場合のテストです。タイトルが長い場合のテストです。タイトルが長い場合のテストです。タイトルが長い場合のテストです。タイトルが長い場合のテストです。タイトルが長い場合のテストです。",
		"division": "配信部署が長い場合のテストです。配信部署が長い場合のテストです。配信部署が長い場合のテストです。配信部署が長い場合のテストです。",
		"productCategoryCd": "DCM0002",
		"targetCd": "1",
		"viewStartYmdHm": "201901030900"
	}, {
		"informationSeqNo": 1110,
		"readCd": "1",
		"actionTypeCd": "0",
		"actionStartYmd": null,
		"actionEndYmd": null,
		"informationContentsTitle": "リンクテスト",
		"division": "投資情報部国内株式課",
		"productCategoryCd": "DCM0001",
		"targetCd": "1",
		"viewStartYmdHm": "199003010000"
	}],
	"errors": {
		"fields": null,
		"global": null
	}
}